[
  {
    "callsign": "PBVF",
    "dataset": "public-global-vessel-identity:v3.0",
    "date": "2025-12-01 05:00",
    "detections": 1,
    "entryTimestamp": "2025-12-01T05:16:55Z",
    "exitTimestamp": "2025-12-01T05:16:55Z",
    "firstTransmissionDate": "2012-01-05T12:01:37Z",
    "flag": "NLD",
    "geartype": "CARGO",
    "imo": "9508794",
    "lastTransmissionDate": "2026-04-24T20:53:12Z",
    "lat": 55.24,
    "lon": 14.130000114440918,
    "mmsi": "246629000",
    "shipName": "AMELAND",
    "vesselId": "59242eddd-d20a-05f3-f8c1-65aa83466888",
    "vesselType": "CARGO",
    "event_metadata": null
  },
  {
    "callsign": "5BDH6",
    "dataset": "public-global-vessel-identity:v3.0",
    "date": "2025-12-01 05:00",
    "detections": 1,
    "entryTimestamp": "2025-12-01T05:16:55Z",
    "exitTimestamp": "2025-12-01T05:16:55Z",
    "firstTransmissionDate": "2022-12-01T16:05:01Z",
    "flag": "CYP",
    "geartype": "CARGO",
    "imo": "9136204",
    "lastTransmissionDate": "2026-04-24T23:58:00Z",
    "lat": 55.18,
    "lon": 14.199999809265137,
    "mmsi": "210549000",
    "shipName": "RIX SPIRIT",
    "vesselId": "3ce0a8aef-f01b-80eb-68bd-a1ba0c6c12c8",
    "vesselType": "CARGO",
    "event_metadata": null
  },
  {
    "callsign": "5BZP4",
    "dataset": "public-global-vessel-identity:v3.0",
    "date": "2025-12-01 05:00",
    "detections": 1,
    "entryTimestamp": "2025-12-01T05:16:55Z",
    "exitTimestamp": "2025-12-01T05:16:55Z",
    "firstTransmissionDate": "2018-05-13T10:53:46Z",
    "flag": "CYP",
    "geartype": "OTHER",
    "imo": "9504035",
    "lastTransmissionDate": "2026-04-24T23:58:06Z",
    "lat": 55.11,
    "lon": 14.130000114440918,
    "mmsi": "209276000",
    "shipName": "ELBWAVE",
    "vesselId": "846cb1608-81e6-54d7-c0b8-4bee06ce3f5c",
    "vesselType": "OTHER",
    "event_metadata": null
  },
  {
    "callsign": "V7A3517",
    "dataset": "public-global-vessel-identity:v3.0",
    "date": "2025-12-01 05:00",
    "detections": 1,
    "entryTimestamp": "2025-12-01T05:16:55Z",
    "exitTimestamp": "2025-12-01T05:16:55Z",
    "firstTransmissionDate": "2025-07-08T07:12:12Z",
    "flag": "MHL",
    "geartype": "CARGO",
    "imo": "9743215",
    "lastTransmissionDate": "2026-04-24T23:48:22Z",
    "lat": 55.21,
    "lon": 14.399999618530273,
    "mmsi": "538011815",
    "shipName": "EUGENIA B",
    "vesselId": "4d30bebfa-abbd-6e47-fbab-4f04b7cf5616",
    "vesselType": "CARGO",
    "event_metadata": null
  },
  {
    "callsign": "OJSH",
    "dataset": "public-global-vessel-identity:v3.0",
    "date": "2025-12-01 05:00",
    "detections": 1,
    "entryTimestamp": "2025-12-01T05:16:55Z",
    "exitTimestamp": "2025-12-01T05:16:55Z",
    "firstTransmissionDate": "2018-02-22T09:07:06Z",
    "flag": "FIN",
    "geartype": "CARGO",
    "imo": "9194282",
    "lastTransmissionDate": "2026-04-24T23:59:49Z",
    "lat": 55.25,
    "lon": 14.300000190734863,
    "mmsi": "230673000",
    "shipName": "PRIMA QUEEN",
    "vesselId": "3b60c55c1-15dd-0f53-dfd5-edb954370ccb",
    "vesselType": "CARGO",
    "event_metadata": null
  },
  {
    "callsign": "OXPQ2",
    "dataset": "public-global-vessel-identity:v3.0",
    "date": "2025-12-04 16:00",
    "detections": 1,
    "entryTimestamp": "2025-12-04T16:53:26Z",
    "exitTimestamp": "2025-12-04T16:53:26Z",
    "firstTransmissionDate": "2018-05-17T13:01:39Z",
    "flag": "DNK",
    "geartype": "PASSENGER",
    "imo": "9812107",
    "lastTransmissionDate": "2026-04-24T23:59:56Z",
    "lat": 55.19,
    "lon": 14.239999771118164,
    "mmsi": "219026000",
    "shipName": "HAMMERSHUS",
    "vesselId": "2cb75b670-08a6-fc17-8fd9-5d9d10a0fbdf",
    "vesselType": "PASSENGER",
    "event_metadata": null
  },
  {
    "callsign": "OVDN",
    "dataset": "public-global-vessel-identity:v3.0",
    "date": "2025-12-04 16:00",
    "detections": 1,
    "entryTimestamp": "2025-12-04T16:53:26Z",
    "exitTimestamp": "2025-12-04T16:53:26Z",
    "firstTransmissionDate": "2018-09-13T16:47:49Z",
    "flag": "DNK",
    "geartype": "OTHER",
    "imo": "",
    "lastTransmissionDate": "2026-04-24T18:28:20Z",
    "lat": 55.16,
    "lon": 14.680000305175781,
    "mmsi": "219000217",
    "shipName": "HDMS SOELOEVEN",
    "vesselId": "22c7ca42d-df50-18b5-713a-a81e9115052c",
    "vesselType": "OTHER",
    "event_metadata": {
      "start": "2025-12-05T12:06:41.000Z",
      "end": "2025-12-06T12:08:08.000Z",
      "id": "efc1703a86346486d884cbd5fc5aab74",
      "type": "port_visit",
      "position": {
        "lat": 55.1155,
        "lon": 14.6758
      },
      "regions": {
        "mpa": [
          "555790698",
          "555543143",
          "555522525"
        ],
        "eez": [
          "5674"
        ],
        "rfmo": [
          "NASCO",
          "ACAP",
          "NAMMCO",
          "ICCAT",
          "IWC",
          "ICES"
        ],
        "fao": [
          "27.3.d.24",
          "27.3.d",
          "27.3",
          "27"
        ],
        "majorFao": [
          "27"
        ],
        "eez12Nm": [
          "5674"
        ],
        "highSeas": [],
        "mpaNoTakePartial": [],
        "mpaNoTake": []
      },
      "boundingBox": [
        14.693334446163684,
        55.105045722833694,
        14.693334446163684,
        55.105045722833694
      ],
      "distances": {
        "startDistanceFromShoreKm": 0,
        "endDistanceFromShoreKm": 0,
        "startDistanceFromPortKm": 0,
        "endDistanceFromPortKm": 0
      },
      "vessel": {
        "id": "22c7ca42d-df50-18b5-713a-a81e9115052c",
        "name": "HDMS SOELOEVEN",
        "ssvid": "219000217",
        "flag": "DNK",
        "type": "other",
        "nextPort": null
      },
      "port_visit": {
        "visitId": "22efc11c118fb011f640e6328d54744f",
        "confidence": "4",
        "durationHrs": 24.024166666666666,
        "startAnchorage": {
          "anchorageId": "46551b1d",
          "atDock": true,
          "distanceFromShoreKm": "0",
          "flag": "DNK",
          "id": "dnk-roenne",
          "lat": 55.105045722833694,
          "lon": 14.693334446163684,
          "name": "ROENNE",
          "topDestination": "BAY LIGHTER"
        },
        "intermediateAnchorage": {
          "anchorageId": "46551b1d",
          "atDock": true,
          "distanceFromShoreKm": "0",
          "flag": "DNK",
          "id": "dnk-roenne",
          "lat": 55.105045722833694,
          "lon": 14.693334446163684,
          "name": "ROENNE",
          "topDestination": "BAY LIGHTER"
        },
        "endAnchorage": {
          "anchorageId": "46551b1d",
          "atDock": true,
          "distanceFromShoreKm": "0",
          "flag": "DNK",
          "id": "dnk-roenne",
          "lat": 55.105045722833694,
          "lon": 14.693334446163684,
          "name": "ROENNE",
          "topDestination": "BAY LIGHTER"
        }
      }
    }
  },
  {
    "callsign": "",
    "dataset": "",
    "date": "2025-12-04 16:00",
    "detections": 1,
    "entryTimestamp": "2025-12-04T16:53:26Z",
    "exitTimestamp": "2025-12-04T16:53:26Z",
    "firstTransmissionDate": "",
    "flag": "",
    "geartype": "",
    "imo": "",
    "lastTransmissionDate": "",
    "lat": 55.2,
    "lon": 14.210000038146973,
    "mmsi": "",
    "shipName": "",
    "vesselId": "",
    "vesselType": "",
    "event_metadata": null
  },
  {
    "callsign": "V2OW7",
    "dataset": "public-global-vessel-identity:v3.0",
    "date": "2025-12-04 16:00",
    "detections": 1,
    "entryTimestamp": "2025-12-04T16:53:26Z",
    "exitTimestamp": "2025-12-04T16:53:26Z",
    "firstTransmissionDate": "2012-01-02T16:28:28Z",
    "flag": "ATG",
    "geartype": "CARGO",
    "imo": "9287807",
    "lastTransmissionDate": "2026-04-24T23:57:57Z",
    "lat": 55.22,
    "lon": 14.40999984741211,
    "mmsi": "305773000",
    "shipName": "VOHBURG",
    "vesselId": "369fc1e02-2678-b669-af58-b2f3ae66a515",
    "vesselType": "CARGO",
    "event_metadata": null
  },
  {
    "callsign": "DFXF",
    "dataset": "public-global-vessel-identity:v3.0",
    "date": "2025-12-04 16:00",
    "detections": 1,
    "entryTimestamp": "2025-12-04T16:53:26Z",
    "exitTimestamp": "2025-12-04T16:53:26Z",
    "firstTransmissionDate": "2014-07-30T09:19:45Z",
    "flag": "DEU",
    "geartype": "CARGO",
    "imo": "9196254",
    "lastTransmissionDate": "2026-04-24T23:59:58Z",
    "lat": 55.16,
    "lon": 14.170000076293945,
    "mmsi": "218797000",
    "shipName": "VAERMLAND",
    "vesselId": "b867aac71-181e-e3fb-ef3b-1267b81caedc",
    "vesselType": "CARGO",
    "event_metadata": null
  },
  {
    "callsign": "5LYK8",
    "dataset": "public-global-vessel-identity:v3.0",
    "date": "2025-12-04 16:00",
    "detections": 1,
    "entryTimestamp": "2025-12-04T16:53:26Z",
    "exitTimestamp": "2025-12-04T16:53:26Z",
    "firstTransmissionDate": "2025-10-31T03:06:26Z",
    "flag": "LBR",
    "geartype": "OTHER",
    "imo": "9312860",
    "lastTransmissionDate": "2026-04-24T13:12:14Z",
    "lat": 55.15,
    "lon": 14.220000267028809,
    "mmsi": "636025638",
    "shipName": "IONIAN SUN",
    "vesselId": "ee20f2f54-4c41-ce6c-ce45-fa136fb6e2cc",
    "vesselType": "OTHER",
    "event_metadata": null
  },
  {
    "callsign": "8PXO8",
    "dataset": "public-global-vessel-identity:v3.0",
    "date": "2025-12-04 16:00",
    "detections": 1,
    "entryTimestamp": "2025-12-04T16:53:26Z",
    "exitTimestamp": "2025-12-04T16:53:26Z",
    "firstTransmissionDate": "2024-03-20T02:01:54Z",
    "flag": "BRB",
    "geartype": "OTHER",
    "imo": "9298662",
    "lastTransmissionDate": "2026-04-24T23:59:54Z",
    "lat": 55.16,
    "lon": 14.109999656677246,
    "mmsi": "314842000",
    "shipName": "MULE",
    "vesselId": "de435d0f3-306c-2869-d119-fff03a975f8f",
    "vesselType": "OTHER",
    "event_metadata": null
  },
  {
    "callsign": "PBDI",
    "dataset": "public-global-vessel-identity:v3.0",
    "date": "2025-12-06 05:00",
    "detections": 1,
    "entryTimestamp": "2025-12-06T05:25:03Z",
    "exitTimestamp": "2025-12-06T05:25:03Z",
    "firstTransmissionDate": "2025-10-14T12:26:31Z",
    "flag": "NLD",
    "geartype": "CARGO",
    "imo": "1046104",
    "lastTransmissionDate": "2026-04-24T23:59:50Z",
    "lat": 55.24,
    "lon": 14.329999923706055,
    "mmsi": "244067000",
    "shipName": "BALTIC SAIL",
    "vesselId": "43c5ec9e1-1026-c273-d280-f0c34b520f53",
    "vesselType": "CARGO",
    "event_metadata": null
  },
  {
    "callsign": "OURV2",
    "dataset": "public-global-vessel-identity:v3.0",
    "date": "2025-12-06 05:00",
    "detections": 1,
    "entryTimestamp": "2025-12-06T05:25:03Z",
    "exitTimestamp": "2025-12-06T05:25:03Z",
    "firstTransmissionDate": "2012-01-01T00:03:55Z",
    "flag": "DNK",
    "geartype": "CARGO",
    "imo": "8104565",
    "lastTransmissionDate": "2026-04-24T23:59:39Z",
    "lat": 55.23,
    "lon": 14.1899995803833,
    "mmsi": "219002392",
    "shipName": "AMANDA",
    "vesselId": "df3528985-5287-a35b-89a0-b2e9c1e6db13",
    "vesselType": "CARGO",
    "event_metadata": null
  },
  {
    "callsign": "YDJY3",
    "dataset": "public-global-vessel-identity:v3.0",
    "date": "2025-12-06 05:00",
    "detections": 1,
    "entryTimestamp": "2025-12-06T05:25:03Z",
    "exitTimestamp": "2025-12-06T05:25:03Z",
    "firstTransmissionDate": "2024-05-08T11:07:06Z",
    "flag": "IDN",
    "geartype": "OTHER",
    "imo": "9388730",
    "lastTransmissionDate": "2026-04-24T23:54:22Z",
    "lat": 55.23,
    "lon": 14.289999961853027,
    "mmsi": "525121076",
    "shipName": "SAVIR TIGER",
    "vesselId": "403dc1002-210e-de4b-331d-b4012153dfa4",
    "vesselType": "OTHER",
    "event_metadata": null
  },
  {
    "callsign": "8POQ",
    "dataset": "public-global-vessel-identity:v3.0",
    "date": "2025-12-06 05:00",
    "detections": 1,
    "entryTimestamp": "2025-12-06T05:25:03Z",
    "exitTimestamp": "2025-12-06T05:25:03Z",
    "firstTransmissionDate": "2025-10-25T08:35:19Z",
    "flag": "BRB",
    "geartype": "OTHER",
    "imo": "9318096",
    "lastTransmissionDate": "2026-04-24T23:59:54Z",
    "lat": 55.15,
    "lon": 14.300000190734863,
    "mmsi": "314001147",
    "shipName": "COSMO SAIL",
    "vesselId": "ddd3f8ebb-b915-bcf6-9d8f-5f463eb99b7f",
    "vesselType": "OTHER",
    "event_metadata": null
  },
  {
    "callsign": "5BNV4",
    "dataset": "public-global-vessel-identity:v3.0",
    "date": "2025-12-06 05:00",
    "detections": 1,
    "entryTimestamp": "2025-12-06T05:25:03Z",
    "exitTimestamp": "2025-12-06T05:25:03Z",
    "firstTransmissionDate": "2016-08-30T13:30:09Z",
    "flag": "CYP",
    "geartype": "CARGO",
    "imo": "9552044",
    "lastTransmissionDate": "2026-04-24T23:59:35Z",
    "lat": 55.09,
    "lon": 14.09000015258789,
    "mmsi": "212584000",
    "shipName": "MIRAMAR",
    "vesselId": "afdb60bd6-6d97-eb03-ef84-c1e3b26c10cc",
    "vesselType": "CARGO",
    "event_metadata": null
  },
  {
    "callsign": "5BRS5",
    "dataset": "public-global-vessel-identity:v3.0",
    "date": "2025-12-06 05:00",
    "detections": 1,
    "entryTimestamp": "2025-12-06T05:25:03Z",
    "exitTimestamp": "2025-12-06T05:25:03Z",
    "firstTransmissionDate": "2021-02-02T09:18:42Z",
    "flag": "CYP",
    "geartype": "CARGO",
    "imo": "9213703",
    "lastTransmissionDate": "2026-04-24T23:59:42Z",
    "lat": 55.21,
    "lon": 14.40999984741211,
    "mmsi": "209982000",
    "shipName": "NINA B",
    "vesselId": "e4a2ba1ec-c786-5395-6e67-1fb8e1abe320",
    "vesselType": "CARGO",
    "event_metadata": null
  }
]